MANIFEST.in
README.txt
setup.cfg
setup.py
atreal/__init__.py
atreal/__init__.pyc
atreal.patchfss.egg-info/PKG-INFO
atreal.patchfss.egg-info/SOURCES.txt
atreal.patchfss.egg-info/dependency_links.txt
atreal.patchfss.egg-info/entry_points.txt
atreal.patchfss.egg-info/namespace_packages.txt
atreal.patchfss.egg-info/not-zip-safe
atreal.patchfss.egg-info/requires.txt
atreal.patchfss.egg-info/top_level.txt
atreal/patchfss/__init__.py
atreal/patchfss/configure.zcml
atreal/patchfss/patch.py