Metadata-Version: 1.0
Name: atreal.patchfss
Version: 1.0.0
Summary: Patch __init.py__ for iw.fss package
Home-page: http://www.atreal.net/
Author: atReal
Author-email: contact@atreal.net
License: GPL
Platform: UNKNOWN
Classifier: Framework :: Plone
Classifier: Programming Language :: Python
Classifier: Topic :: Software Development :: Libraries :: Python Modules
